[
  {
    "id": "workday:citi/2:/job/Pune-Maharashtra-India/Digital-S-W-Engineer-Senior-Analyst-SDE---Backend-Development---C12---PUNE-CHENNAI_26970959",
    "company": "citi",
    "title": "Digital Software Engineer Senior Analyst - Backend Development - Assistant Vice President",
    "location": "2 Locations",
    "url": "https://citi.wd5.myworkdayjobs.com/en-US/2/job/Pune-Maharashtra-India/Digital-S-W-Engineer-Senior-Analyst-SDE---Backend-Development---C12---PUNE-CHENNAI_26970959",
    "description_html": " The Digital S/W Engineer Senior Analyst SDE - Web Development is a Technology/ Engineering role involving both development and Testing. As a member of the SCRUM team, you will be delivering Customer facing Banking and/or Credit Card features on digital channels such as Browser and Mobile. You will be involved in all stages of the Agile SDLC cycle. It includes but not limited to (a)\u00a0 Requirement analysis : Grooming of user stories, Story pointing, decomposing big stories into smaller stories and define acceptance criteria. (b)\u00a0 Design \u00a0 Review: \u00a0Reviewing screens, flows, features, and customer communications (emails, SMS\u2019s, notifications, PDF documents) and making sure that they are consistent with user story acceptance criteria (c)\u00a0 Software development : Developing, configuring and debugging applications comprising of web frontend and Micro services. (d)\u00a0 Validations: \u00a0Creating automated and manual test scripts on BDD (Behavior Based Development) framework, executing test scripts. Identifying, triaging and fixing any defects. Conditioning and maintaining the test data. (e)\u00a0 Artifact Ownership: \u00a0Creating and maintaining testing artifacts such as Test plans and Exit reports and maintaining traceability as per SDLC guidelines. Maintaining SDLC hygiene involving stories. Test cases and defects. Ensuring that no untested code goes out to production. (f)\u00a0 SDLC Process and Standards: \u00a0Adhering to ADA (Americans with Disability Act) Guidelines, participating in retrospectives, process improvement workshops, audits and performing root cause analysis. (g)\u00a0 Postproduction \u00a0 support : Supporting the technical check outs during release go live and postproduction activities.     Responsibilities     Turn tech stack and application design into code on multiple development platforms (e.g. Angular, Java spring boot services).    Ability to use AI tools like Copilot for code generation, refactoring, and debugging.    Develop and maintain BDD (Behavior Driven Development) automated and manual scripts in a code repository. Execute them and maintain test results in a test management tool for further reporting and establishing traceability. Create Jenkins jobs and plug in to CI-CD pipeline.    Experience using AI tools accelerate unit tests, API scaffolding, Angular components, and Spring Boot boilerplate.    Actively participate in the entire software development cycle involving development, integration and E2E testing in a CI/CD environment (RTC, Jenkins). Automate and enable shift left.    Accountable for development, design, construction, testing and implementation and write secure, stable, testable and maintainable code.    Continuously build, maintain documentation for your features and develop SME \u2013 Subject Matter Expertise in specific areas covering end to end flows, from digital to downstream to external partners.    Analyze root causes for application issues and performance concerns. Collaborate within the scrum team, across other impacted downstream or upstream entities and external partners to solve the issues. Triage, track and report defects followed by prioritization, fix and closure.    Adhere to SDLC control processes. Suggest and implement continuous improvements.    Apart from functional validations to meet the acceptance criteria, validate Responsive Web Design and validate ADA Accessibility using screen readers such as NVDA, Voiceover and Talkback, code scan using Axe, perform CCA and be comfortable with other ADA tools and processes.    Review metrics and proactively seek out new and improved ways for visibility ensuring your program stays on track or excels in meeting the organization objectives.    Work in a fast-paced environment involving onshore offshore teams.       Education, Qualification &amp; Certifications     Bachelor\u2019s degree in computer engineering or related fields in STEM or comparable work experience.    5-8 years of Full stack mobile Development and Testing experience in a fast-paced environment.    Familiarity with Behavior-Driven Development (BDD) test automation using Selenium with Cucumber framework.    Preferable to have experience with cloud-based development platforms such as OpenShift.    Working knowledge of JIRA, Zephyr, Confluence SharePoint, Microsoft Teams and Microsoft office suit.    Self-motivated and ready to take ownership.    Excellent written, oral communication and interpersonal skills                  ------------------------------------------------------               Job Family Group:   Technology             ------------------------------------------------------               Job Family:  Applications Development         ------------------------------------------------------           Time Type:  Full time   ------------------------------------------------------     Most Relevant Skills   Please see the requirements listed above. ------------------------------------------------------   Other Relevant Skills   For complementary skills, please see above and/or contact the recruiter. ------------------------------------------------------    Citi is an equal opportunity employer, and qualified candidates will receive consideration without regard to their race, color, religion, sex, sexual orientation, gender identity, national origin, disability, status as a protected veteran, or any other characteristic protected by law.      \u00a0      If you are a person with a disability and need a reasonable accommodation to use our search tools and/or apply for a career opportunity review     Accessibility at Citi  .      View Citi\u2019s   EEO Policy Statement   and the   Know Your Rights   poster.   ",
    "updated_at": "Posted Today",
    "source": "workday",
    "score": 75
  },
  {
    "id": "workday:citi/2:/job/Pune-Maharashtra-India/Digital-S-W-Engineer-Senior-Analyst-SDE---Backend-Development---C12---PUNE-CHENNAI_26970956",
    "company": "citi",
    "title": "Digital Software Engineer Senior Analyst - Backend Development - Assistant Vice President",
    "location": "2 Locations",
    "url": "https://citi.wd5.myworkdayjobs.com/en-US/2/job/Pune-Maharashtra-India/Digital-S-W-Engineer-Senior-Analyst-SDE---Backend-Development---C12---PUNE-CHENNAI_26970956",
    "description_html": " The Digital S/W Engineer Senior Analyst SDE - Web Development is a Technology/ Engineering role involving both development and Testing. As a member of the SCRUM team, you will be delivering Customer facing Banking and/or Credit Card features on digital channels such as Browser and Mobile. You will be involved in all stages of the Agile SDLC cycle. It includes but not limited to (a)\u00a0 Requirement analysis : Grooming of user stories, Story pointing, decomposing big stories into smaller stories and define acceptance criteria. (b)\u00a0 Design \u00a0 Review: \u00a0Reviewing screens, flows, features, and customer communications (emails, SMS\u2019s, notifications, PDF documents) and making sure that they are consistent with user story acceptance criteria (c)\u00a0 Software development : Developing, configuring and debugging applications comprising of web frontend and Micro services. (d)\u00a0 Validations: \u00a0Creating automated and manual test scripts on BDD (Behavior Based Development) framework, executing test scripts. Identifying, triaging and fixing any defects. Conditioning and maintaining the test data. (e)\u00a0 Artifact Ownership: \u00a0Creating and maintaining testing artifacts such as Test plans and Exit reports and maintaining traceability as per SDLC guidelines. Maintaining SDLC hygiene involving stories. Test cases and defects. Ensuring that no untested code goes out to production. (f)\u00a0 SDLC Process and Standards: \u00a0Adhering to ADA (Americans with Disability Act) Guidelines, participating in retrospectives, process improvement workshops, audits and performing root cause analysis. (g)\u00a0 Postproduction \u00a0 support : Supporting the technical check outs during release go live and postproduction activities.     Responsibilities     Turn tech stack and application design into code on multiple development platforms (e.g. Angular, Java spring boot services).    Ability to use AI tools like Copilot for code generation, refactoring, and debugging.    Develop and maintain BDD (Behavior Driven Development) automated and manual scripts in a code repository. Execute them and maintain test results in a test management tool for further reporting and establishing traceability. Create Jenkins jobs and plug in to CI-CD pipeline.    Experience using AI tools accelerate unit tests, API scaffolding, Angular components, and Spring Boot boilerplate.    Actively participate in the entire software development cycle involving development, integration and E2E testing in a CI/CD environment (RTC, Jenkins). Automate and enable shift left.    Accountable for development, design, construction, testing and implementation and write secure, stable, testable and maintainable code.    Continuously build, maintain documentation for your features and develop SME \u2013 Subject Matter Expertise in specific areas covering end to end flows, from digital to downstream to external partners.    Analyze root causes for application issues and performance concerns. Collaborate within the scrum team, across other impacted downstream or upstream entities and external partners to solve the issues. Triage, track and report defects followed by prioritization, fix and closure.    Adhere to SDLC control processes. Suggest and implement continuous improvements.    Apart from functional validations to meet the acceptance criteria, validate Responsive Web Design and validate ADA Accessibility using screen readers such as NVDA, Voiceover and Talkback, code scan using Axe, perform CCA and be comfortable with other ADA tools and processes.    Review metrics and proactively seek out new and improved ways for visibility ensuring your program stays on track or excels in meeting the organization objectives.    Work in a fast-paced environment involving onshore offshore teams.       Education, Qualification &amp; Certifications     Bachelor\u2019s degree in computer engineering or related fields in STEM or comparable work experience.    5-8 years of Full stack mobile Development and Testing experience in a fast-paced environment.    Familiarity with Behavior-Driven Development (BDD) test automation using Selenium with Cucumber framework.    Preferable to have experience with cloud-based development platforms such as OpenShift.    Working knowledge of JIRA, Zephyr, Confluence SharePoint, Microsoft Teams and Microsoft office suit.    Self-motivated and ready to take ownership.    Excellent written, oral communication and interpersonal skills                  ------------------------------------------------------               Job Family Group:   Technology             ------------------------------------------------------               Job Family:  Applications Development         ------------------------------------------------------           Time Type:  Full time   ------------------------------------------------------     Most Relevant Skills   Please see the requirements listed above. ------------------------------------------------------   Other Relevant Skills   For complementary skills, please see above and/or contact the recruiter. ------------------------------------------------------    Citi is an equal opportunity employer, and qualified candidates will receive consideration without regard to their race, color, religion, sex, sexual orientation, gender identity, national origin, disability, status as a protected veteran, or any other characteristic protected by law.      \u00a0      If you are a person with a disability and need a reasonable accommodation to use our search tools and/or apply for a career opportunity review     Accessibility at Citi  .      View Citi\u2019s   EEO Policy Statement   and the   Know Your Rights   poster.   ",
    "updated_at": "Posted Today",
    "source": "workday",
    "score": 75
  },
  {
    "id": "workday:citi/2:/job/Pune-Maharashtra-India/Digital-S-W-Engineer-Senior-Analyst-SDE---Backend-Development--C12---PUNE-CHENNAI_26970953",
    "company": "citi",
    "title": "Digital Software Engineer Senior Analyst- Backend Development- Assistant Vice President",
    "location": "2 Locations",
    "url": "https://citi.wd5.myworkdayjobs.com/en-US/2/job/Pune-Maharashtra-India/Digital-S-W-Engineer-Senior-Analyst-SDE---Backend-Development--C12---PUNE-CHENNAI_26970953",
    "description_html": " The Digital S/W Engineer Senior Analyst SDE - Web Development is a Technology/ Engineering role involving both development and Testing. As a member of the SCRUM team, you will be delivering Customer facing Banking and/or Credit Card features on digital channels such as Browser and Mobile. You will be involved in all stages of the Agile SDLC cycle. It includes but not limited to (a)\u00a0 Requirement analysis : Grooming of user stories, Story pointing, decomposing big stories into smaller stories and define acceptance criteria. (b)\u00a0 Design \u00a0 Review: \u00a0Reviewing screens, flows, features, and customer communications (emails, SMS\u2019s, notifications, PDF documents) and making sure that they are consistent with user story acceptance criteria (c)\u00a0 Software development : Developing, configuring and debugging applications comprising of web frontend and Micro services. (d)\u00a0 Validations: \u00a0Creating automated and manual test scripts on BDD (Behavior Based Development) framework, executing test scripts. Identifying, triaging and fixing any defects. Conditioning and maintaining the test data. (e)\u00a0 Artifact Ownership: \u00a0Creating and maintaining testing artifacts such as Test plans and Exit reports and maintaining traceability as per SDLC guidelines. Maintaining SDLC hygiene involving stories. Test cases and defects. Ensuring that no untested code goes out to production. (f)\u00a0 SDLC Process and Standards: \u00a0Adhering to ADA (Americans with Disability Act) Guidelines, participating in retrospectives, process improvement workshops, audits and performing root cause analysis. (g)\u00a0 Postproduction \u00a0 support : Supporting the technical check outs during release go live and postproduction activities.     Responsibilities     Turn tech stack and application design into code on multiple development platforms (e.g. Angular, Java spring boot services).    Ability to use AI tools like Copilot for code generation, refactoring, and debugging.    Develop and maintain BDD (Behavior Driven Development) automated and manual scripts in a code repository. Execute them and maintain test results in a test management tool for further reporting and establishing traceability. Create Jenkins jobs and plug in to CI-CD pipeline.    Experience using AI tools accelerate unit tests, API scaffolding, Angular components, and Spring Boot boilerplate.    Actively participate in the entire software development cycle involving development, integration and E2E testing in a CI/CD environment (RTC, Jenkins). Automate and enable shift left.    Accountable for development, design, construction, testing and implementation and write secure, stable, testable and maintainable code.    Continuously build, maintain documentation for your features and develop SME \u2013 Subject Matter Expertise in specific areas covering end to end flows, from digital to downstream to external partners.    Analyze root causes for application issues and performance concerns. Collaborate within the scrum team, across other impacted downstream or upstream entities and external partners to solve the issues. Triage, track and report defects followed by prioritization, fix and closure.    Adhere to SDLC control processes. Suggest and implement continuous improvements.    Apart from functional validations to meet the acceptance criteria, validate Responsive Web Design and validate ADA Accessibility using screen readers such as NVDA, Voiceover and Talkback, code scan using Axe, perform CCA and be comfortable with other ADA tools and processes.    Review metrics and proactively seek out new and improved ways for visibility ensuring your program stays on track or excels in meeting the organization objectives.    Work in a fast-paced environment involving onshore offshore teams.       Education, Qualification &amp; Certifications     Bachelor\u2019s degree in computer engineering or related fields in STEM or comparable work experience.    5-8 years of Full stack mobile Development and Testing experience in a fast-paced environment.    Familiarity with Behavior-Driven Development (BDD) test automation using Selenium with Cucumber framework.    Preferable to have experience with cloud-based development platforms such as OpenShift.    Working knowledge of JIRA, Zephyr, Confluence SharePoint, Microsoft Teams and Microsoft office suit.    Self-motivated and ready to take ownership.    Excellent written, oral communication and interpersonal skills                ------------------------------------------------------               Job Family Group:   Technology             ------------------------------------------------------               Job Family:  Applications Development         ------------------------------------------------------           Time Type:  Full time   ------------------------------------------------------     Most Relevant Skills   Please see the requirements listed above. ------------------------------------------------------   Other Relevant Skills   For complementary skills, please see above and/or contact the recruiter. ------------------------------------------------------    Citi is an equal opportunity employer, and qualified candidates will receive consideration without regard to their race, color, religion, sex, sexual orientation, gender identity, national origin, disability, status as a protected veteran, or any other characteristic protected by law.      \u00a0      If you are a person with a disability and need a reasonable accommodation to use our search tools and/or apply for a career opportunity review     Accessibility at Citi  .      View Citi\u2019s   EEO Policy Statement   and the   Know Your Rights   poster.   ",
    "updated_at": "Posted Today",
    "source": "workday",
    "score": 75
  },
  {
    "id": "workday:citi/2:/job/Pune-Maharashtra-India/Digital-S-W-Engineer-Senior-Analyst-SDE---Web-Development---C12---PUNE-CHENNAI_26970951",
    "company": "citi",
    "title": "Digital Software Engineer Senior Analyst - Web Development - Assistant Vice President",
    "location": "2 Locations",
    "url": "https://citi.wd5.myworkdayjobs.com/en-US/2/job/Pune-Maharashtra-India/Digital-S-W-Engineer-Senior-Analyst-SDE---Web-Development---C12---PUNE-CHENNAI_26970951",
    "description_html": " The Digital S/W Engineer Senior Analyst SDE - Web Development is a Technology/ Engineering role involving both development and Testing. As a member of the SCRUM team, you will be delivering Customer facing Banking and/or Credit Card features on digital channels such as Browser and Mobile. You will be involved in all stages of the Agile SDLC cycle. It includes but not limited to (a)\u00a0 Requirement analysis : Grooming of user stories, Story pointing, decomposing big stories into smaller stories and define acceptance criteria. (b)\u00a0 Design \u00a0 Review: \u00a0Reviewing screens, flows, features, and customer communications (emails, SMS\u2019s, notifications, PDF documents) and making sure that they are consistent with user story acceptance criteria (c)\u00a0 Software development : Developing, configuring and debugging applications comprising of web frontend and Micro services. (d)\u00a0 Validations: \u00a0Creating automated and manual test scripts on BDD (Behavior Based Development) framework, executing test scripts. Identifying, triaging and fixing any defects. Conditioning and maintaining the test data. (e)\u00a0 Artifact Ownership: \u00a0Creating and maintaining testing artifacts such as Test plans and Exit reports and maintaining traceability as per SDLC guidelines. Maintaining SDLC hygiene involving stories. Test cases and defects. Ensuring that no untested code goes out to production. (f)\u00a0 SDLC Process and Standards: \u00a0Adhering to ADA (Americans with Disability Act) Guidelines, participating in retrospectives, process improvement workshops, audits and performing root cause analysis. (g)\u00a0 Postproduction \u00a0 support : Supporting the technical check outs during release go live and postproduction activities.     Responsibilities     Turn tech stack and application design into code on multiple development platforms (e.g. Angular, Java spring boot services).    Ability to use AI tools like Copilot for code generation, refactoring, and debugging.    Develop and maintain BDD (Behavior Driven Development) automated and manual scripts in a code repository. Execute them and maintain test results in a test management tool for further reporting and establishing traceability. Create Jenkins jobs and plug in to CI-CD pipeline.    Experience using AI tools accelerate unit tests, API scaffolding, Angular components, and Spring Boot boilerplate.    Actively participate in the entire software development cycle involving development, integration and E2E testing in a CI/CD environment (RTC, Jenkins). Automate and enable shift left.    Accountable for development, design, construction, testing and implementation and write secure, stable, testable and maintainable code.    Continuously build, maintain documentation for your features and develop SME \u2013 Subject Matter Expertise in specific areas covering end to end flows, from digital to downstream to external partners.    Analyze root causes for application issues and performance concerns. Collaborate within the scrum team, across other impacted downstream or upstream entities and external partners to solve the issues. Triage, track and report defects followed by prioritization, fix and closure.    Adhere to SDLC control processes. Suggest and implement continuous improvements.    Apart from functional validations to meet the acceptance criteria, validate Responsive Web Design and validate ADA Accessibility using screen readers such as NVDA, Voiceover and Talkback, code scan using Axe, perform CCA and be comfortable with other ADA tools and processes.    Review metrics and proactively seek out new and improved ways for visibility ensuring your program stays on track or excels in meeting the organization objectives.    Work in a fast-paced environment involving onshore offshore teams.       Education, Qualification &amp; Certifications     Bachelor\u2019s degree in computer engineering or related fields in STEM or comparable work experience.    5-8 years of Full stack mobile Development and Testing experience in a fast-paced environment.    Familiarity with Behavior-Driven Development (BDD) test automation using Selenium with Cucumber framework.    Preferable to have experience with cloud-based development platforms such as OpenShift.    Working knowledge of JIRA, Zephyr, Confluence SharePoint, Microsoft Teams and Microsoft office suit.    Self-motivated and ready to take ownership.    Excellent written, oral communication and interpersonal skills                  ------------------------------------------------------               Job Family Group:   Technology             ------------------------------------------------------               Job Family:  Applications Development         ------------------------------------------------------           Time Type:  Full time   ------------------------------------------------------     Most Relevant Skills   Please see the requirements listed above. ------------------------------------------------------   Other Relevant Skills   For complementary skills, please see above and/or contact the recruiter. ------------------------------------------------------    Citi is an equal opportunity employer, and qualified candidates will receive consideration without regard to their race, color, religion, sex, sexual orientation, gender identity, national origin, disability, status as a protected veteran, or any other characteristic protected by law.      \u00a0      If you are a person with a disability and need a reasonable accommodation to use our search tools and/or apply for a career opportunity review     Accessibility at Citi  .      View Citi\u2019s   EEO Policy Statement   and the   Know Your Rights   poster.   ",
    "updated_at": "Posted Today",
    "source": "workday",
    "score": 68
  },
  {
    "id": "workday:citi/2:/job/Pune-Maharashtra-India/Digital-S-W-Engineer-Senior-Analyst-SDE---Web-Development_26970947",
    "company": "citi",
    "title": "Digital Software Engineer Senior Analyst - Web Development",
    "location": "2 Locations",
    "url": "https://citi.wd5.myworkdayjobs.com/en-US/2/job/Pune-Maharashtra-India/Digital-S-W-Engineer-Senior-Analyst-SDE---Web-Development_26970947",
    "description_html": " The Digital S/W Engineer Senior Analyst SDE - Web Development is a Technology/ Engineering role involving both development and Testing. As a member of the SCRUM team, you will be delivering Customer facing Banking and/or Credit Card features on digital channels such as Browser and Mobile. You will be involved in all stages of the Agile SDLC cycle. It includes but not limited to (a)\u00a0 Requirement analysis : Grooming of user stories, Story pointing, decomposing big stories into smaller stories and define acceptance criteria. (b)\u00a0 Design \u00a0 Review: \u00a0Reviewing screens, flows, features, and customer communications (emails, SMS\u2019s, notifications, PDF documents) and making sure that they are consistent with user story acceptance criteria (c)\u00a0 Software development : Developing, configuring and debugging applications comprising of web frontend and Micro services. (d)\u00a0 Validations: \u00a0Creating automated and manual test scripts on BDD (Behavior Based Development) framework, executing test scripts. Identifying, triaging and fixing any defects. Conditioning and maintaining the test data. (e)\u00a0 Artifact Ownership: \u00a0Creating and maintaining testing artifacts such as Test plans and Exit reports and maintaining traceability as per SDLC guidelines. Maintaining SDLC hygiene involving stories. Test cases and defects. Ensuring that no untested code goes out to production. (f)\u00a0 SDLC Process and Standards: \u00a0Adhering to ADA (Americans with Disability Act) Guidelines, participating in retrospectives, process improvement workshops, audits and performing root cause analysis. (g)\u00a0 Postproduction \u00a0 support : Supporting the technical check outs during release go live and postproduction activities.     Responsibilities     Turn tech stack and application design into code on multiple development platforms (e.g. Angular, Java spring boot services).    Ability to use AI tools like Copilot for code generation, refactoring, and debugging.    Develop and maintain BDD (Behavior Driven Development) automated and manual scripts in a code repository. Execute them and maintain test results in a test management tool for further reporting and establishing traceability. Create Jenkins jobs and plug in to CI-CD pipeline.    Experience using AI tools accelerate unit tests, API scaffolding, Angular components, and Spring Boot boilerplate.    Actively participate in the entire software development cycle involving development, integration and E2E testing in a CI/CD environment (RTC, Jenkins). Automate and enable shift left.    Accountable for development, design, construction, testing and implementation and write secure, stable, testable and maintainable code.    Continuously build, maintain documentation for your features and develop SME \u2013 Subject Matter Expertise in specific areas covering end to end flows, from digital to downstream to external partners.    Analyze root causes for application issues and performance concerns. Collaborate within the scrum team, across other impacted downstream or upstream entities and external partners to solve the issues. Triage, track and report defects followed by prioritization, fix and closure.    Adhere to SDLC control processes. Suggest and implement continuous improvements.    Apart from functional validations to meet the acceptance criteria, validate Responsive Web Design and validate ADA Accessibility using screen readers such as NVDA, Voiceover and Talkback, code scan using Axe, perform CCA and be comfortable with other ADA tools and processes.    Review metrics and proactively seek out new and improved ways for visibility ensuring your program stays on track or excels in meeting the organization objectives.    Work in a fast-paced environment involving onshore offshore teams.       Education, Qualification &amp; Certifications     Bachelor\u2019s degree in computer engineering or related fields in STEM or comparable work experience.    5-8 years of Full stack mobile Development and Testing experience in a fast-paced environment.    Familiarity with Behavior-Driven Development (BDD) test automation using Selenium with Cucumber framework.    Preferable to have experience with cloud-based development platforms such as OpenShift.    Working knowledge of JIRA, Zephyr, Confluence SharePoint, Microsoft Teams and Microsoft office suit.    Self-motivated and ready to take ownership.    Excellent written, oral communication and interpersonal skills                  ------------------------------------------------------               Job Family Group:   Technology             ------------------------------------------------------               Job Family:  Applications Development         ------------------------------------------------------           Time Type:  Full time   ------------------------------------------------------     Most Relevant Skills   Please see the requirements listed above. ------------------------------------------------------   Other Relevant Skills   For complementary skills, please see above and/or contact the recruiter. ------------------------------------------------------    Citi is an equal opportunity employer, and qualified candidates will receive consideration without regard to their race, color, religion, sex, sexual orientation, gender identity, national origin, disability, status as a protected veteran, or any other characteristic protected by law.      \u00a0      If you are a person with a disability and need a reasonable accommodation to use our search tools and/or apply for a career opportunity review     Accessibility at Citi  .      View Citi\u2019s   EEO Policy Statement   and the   Know Your Rights   poster.   ",
    "updated_at": "Posted Today",
    "source": "workday",
    "score": 68
  }
]