[
  {
    "id": "workday:workday/Workday:/job/USA-MA-Boston/Sr-Cloud-Engineer_JR-0108521-2",
    "company": "workday",
    "title": "Sr Cloud Engineer",
    "location": "USA, MA, Boston",
    "url": "https://workday.wd5.myworkdayjobs.com/en-US/Workday/job/USA-MA-Boston/Sr-Cloud-Engineer_JR-0108521-2",
    "description_html": "  Your work days are brighter here.    We\u2019re obsessed with making hard work pay off, for our people, our customers, and the world around us. As a Fortune 500 company and a leading AI platform for managing people, money, and agents, we\u2019re shaping the future of work so teams can reach their potential and focus on what matters most. The minute you join, you\u2019ll feel it. Not just in the products we build, but in how we show up for each other. Our culture is rooted in integrity, empathy, and shared enthusiasm. We\u2019re in this together, tackling big challenges with bold ideas and genuine care. We look for curious minds and courageous collaborators who bring sun-drenched optimism and drive. Whether you&#39;re building smarter solutions, supporting customers, or creating a space where everyone belongs, you\u2019ll do meaningful work with Workmates who\u2019ve got your back. In return, we\u2019ll give you the trust to take risks, the tools to grow, the skills to develop and the support of a company invested in you for the long haul. So, if you want to inspire a brighter work day for everyone, including yourself, you\u2019ve found a match in Workday, and we hope to be a match for you too.        About the Team     About the Role    Maintains the relationships and monitors performance of information technology vendors contracted for the delivery of outsourced services. Public (AWS, Azure, GCP) analysis of actuals to budget / forecast, analyze key areas of waste and optimization, and utilization rates. Extract and analyze large scale data within cloud billing and usage, to support senior engineering and financial partners in decision making. Describe and implement opportunities for price optimizations initiatives with public cloud vendors including Reserved Instances (RIs) and Monthly Savings Plans. Identification, implementation, and maintenance of AWS Key Performance Indicators. Extract and analyze sophisticated datasets using well optimized SQL queries, Python and R. Configure analytics platforms Looker and Portal Lightdash to create dashboards and reports to provide business insights and drive business development. Monitor service level objectives by building Grafana dashboards to track metrics like service status. Create alerts for significant changes in key metrics for teams to address anomalies in time.    Salary Range: $161,300 - $241,900    About You     Basic Qualifications   Master&#39;s degree in Data Science, Data Analytics or related field.  Completion of a university level course, research project, internship, or thesis in Public cloud GCP BigQuery data analysis;  Completion of a university level course, research project, internship, or thesis in Cloud data machine learning modeling;  Completion of a university level course, research project, internship, or thesis in Cloud data visualization using Python and SQL;  Completion of a university level course, research project, internship, or thesis in Extracting and processing large-scale datasets using SQL queries and Python; and  Completion of a university level course, research project, internship, or thesis in Configuring analytics platforms comparable to Looker to build dashboards and create reports.    Workday Pay Transparency Statement    Workday pay ranges vary based on work location. As a part of the total compensation package, this role may be eligible for the Workday Bonus Plan or a role-specific commission/bonus, as well as annual refresh stock grants. Recruiters can share more detail during the hiring process. Each candidate\u2019s compensation offer will be based on multiple factors including, but not limited to, geography, experience, skills, job duties, and business need, among other things. For more information regarding Workday\u2019s comprehensive benefits, please  click here .  \u00a0  \u00a0 Primary Location: USA.MA.Boston \u00a0  \u00a0     Our Approach to Flexible Work  \u00a0   Workday uses a hybrid Flex Work Model. Most roles require at least 50% in-person time each quarter in a Workday office or with customers, prospects, or partners, with specific expectations varying by role, team, country, and business needs.    Pursuant to applicable Fair Chance law, Workday will consider for employment qualified applicants with arrest and conviction records.   Workday is an Equal Opportunity Employer including individuals with disabilities and protected veterans.   Workday is committed to providing reasonable accommodations for qualified individuals during our application process, in order to perform one or more essential functions of their job, as well as regarding the use of AI tools for employment decision-making to any degree. Please see below for more details including how to request an accommodation as a qualified veteran, due to a disability or for religious reasons, or as otherwise provided under applicable law.      Workday prohibits taking adverse action against any candidate or employee for reporting a possible violation of this policy, requesting one or more work accommodations, exercising a privacy right, or cooperating in an investigation in accordance with applicable law. Any employee who retaliates against a candidate or employee for doing so may be subject to disciplinary action, up to and including termination of employment, to the fullest extent allowable under applicable law.      If you require a reasonable accommodation, you should open a People Guide Request (current employees only), or you may email accommodations&#64;workday.com, as far in advance as possible.       Are you being referred to one of our roles? If so, ask your connection at Workday about our Employee Referral process!   At Workday, we value our candidates\u2019 privacy and data security.\u00a0 Workday will never ask candidates to apply to jobs through websites that are not Workday Careers.\u00a0  \u00a0\u00a0  Please be aware of sites that may ask for you to input your data in connection with a job posting that appears to be from Workday but is not.  \u00a0\u00a0  In addition, Workday will never ask candidates to pay a recruiting fee, or pay for consulting or coaching services, in order to apply for a job at Workday. ",
    "updated_at": "Posted Today",
    "source": "workday",
    "score": 87
  }
]